{
  "id": "session_1741187455",
  "goal": {
    "id": "goal_1741187455",
    "description": "Identify molecular mechanisms that link chronic inflammation to Alzheimer's disease progression",
    "domain": "neuroscience",
    "constraints": [],
    "background": "Recent studies suggest neuroinflammation plays a key role in neurodegeneration, but the exact mechanisms remain unclear.",
    "created_at": "2025-03-05T12:10:55.544227"
  },
  "hypotheses": [],
  "iterations_completed": 0,
  "max_iterations": 5,
  "state": "initial",
  "feedback_history": [],
  "top_hypotheses": [],
  "tool_usage": {},
  "started_at": "2025-03-05T12:10:55.544227",
  "completed_at": null,
  "update_time": 1741187455.5442274
}